LICENSE
README.md
setup.cfg
setup.py
coingenerator/colors.py
coingenerator/exporter.py
coingenerator/getQuark.py
coingenerator/getTransactions.py
coingenerator/prepare.py
coingenerator/prepareGraph.py
coingenerator/requester.py
coingenerator/test_address_list1.py
coingenerator/test_address_list2.py
coingenerator/test_address_list3.py
coingenerator/utils.py
coingenerator.egg-info/PKG-INFO
coingenerator.egg-info/SOURCES.txt
coingenerator.egg-info/dependency_links.txt
coingenerator.egg-info/requires.txt
coingenerator.egg-info/top_level.txt