Metadata-Version: 2.1
Name: coingenerator
Version: 1.0.1
Summary: Coin-help-package For transaction Analyze.
Home-page: UNKNOWN
Author: Zort Labs
License: Python Script
Platform: UNKNOWN
Provides-Extra: dev
License-File: LICENSE
